LICENSE
MANIFEST.in
README.rst
setup.py
pygeocode/__init__.py
pygeocode/geocoder.py
pygeocode/util.py
pygeocode.egg-info/PKG-INFO
pygeocode.egg-info/SOURCES.txt
pygeocode.egg-info/dependency_links.txt
pygeocode.egg-info/namespace_packages.txt
pygeocode.egg-info/requires.txt
pygeocode.egg-info/top_level.txt
pygeocode/test/__init__.py
pygeocode/test/test_geocoder.py
pygeocode/test/util.py