Metadata-Version: 1.1
Name: pygeocode
Version: 0.0.4
Summary: pygeocode -- Wrapper for several public geocoding APIs
Home-page: https://github.com/thelinuxkid/pygeocode
Author: Andres Buritica
Author-email: andres@thelinuxkid.com
License: MIT
Platform: UNKNOWN
Classifier: Development Status :: 4 - Beta
Classifier: Intended Audience :: Developers
Classifier: Natural Language :: English
Classifier: License :: OSI Approved :: MIT License
Classifier: Programming Language :: Python
Classifier: Programming Language :: Python :: 2.7
